AmanCalc/__init__.py
AmanCalc-2.0.dist-info/LICENSE.txt
AmanCalc-2.0.dist-info/METADATA
AmanCalc-2.0.dist-info/WHEEL
AmanCalc-2.0.dist-info/top_level.txt
AmanCalc-2.0.dist-info/RECORD
