Metadata-Version: 2.1
Name: AmanCalc
Version: 2.0
Summary: Use For Calculation Of Two Numbers.
Home-page: UNKNOWN
Author: Aman Mishra
Author-email: mishra.aman180@gmail.com
License: UNKNOWN
Platform: UNKNOWN
Classifier: Programming Language :: Python :: 3
Classifier: License :: OSI Approved :: MIT License
Classifier: Operating System :: OS Independent
